scrolls/__init__.py
scrolls/__main__.py
scrolls/builtins.py
scrolls/containers.py
scrolls/datatypes.py
scrolls/errors.py
scrolls/ast/__init__.py
scrolls/ast/ast_constants.py
scrolls/ast/ast_errors.py
scrolls/ast/streams.py
scrolls/ast/syntax.py
scrolls/ast/tokenizer.py
scrolls/ext/__init__.py
scrolls/ext/callbase.py
scrolls/interpreter/__init__.py
scrolls/interpreter/callhandler.py
scrolls/interpreter/interpreter_errors.py
scrolls/interpreter/run.py
scrolls/interpreter/state.py
scrolls/interpreter/struct.py
scrolls_py-0.4.0.dist-info/LICENSE
scrolls_py-0.4.0.dist-info/METADATA
scrolls_py-0.4.0.dist-info/WHEEL
scrolls_py-0.4.0.dist-info/top_level.txt
scrolls_py-0.4.0.dist-info/RECORD
