Metadata-Version: 2.1
Name: scrolls-py
Version: 0.4.0
Summary: A customizable interpreted microlanguage designed to run untrusted code.
Home-page: https://github.com/a-bison/scrolls-py
Author: a-bison
Author-email: aliteralbison@protonmail.com
Classifier: Programming Language :: Python :: 3
Classifier: License :: OSI Approved :: BSD License
Classifier: Intended Audience :: Developers
Classifier: Operating System :: OS Independent
Classifier: Topic :: Software Development :: Interpreters
Classifier: Topic :: Software Development :: User Interfaces
Classifier: Topic :: Utilities
Requires-Python: >=3.9
License-File: LICENSE
